AUTHORS
LICENSE
MANIFEST.in
README.rst
setup.py
gallery/__init__.py
gallery/admin.py
gallery/generator.py
gallery/models.py
gallery/tests.py
gallery/urls.py
gallery/views.py
gallery/fixtures/photosizes.json
gallery/media/gallery/flash/flowplayer-3.1.5.swf
gallery/media/gallery/flash/flowplayercontrols-3.1.5.swf
gallery/media/gallery/js/flowplayer-3.2.0.min.js
gallery/templates/gallery/gallery_detail.html
gallery/templates/gallery/gallery_list.html
gallery/templates/gallery/ajax/galleriffic_galleryimage.html
gallery/templates/gallery/ajax/galleriffic_videoembed.html
gallery/templates/gallery/ajax/galleriffic_videofile.html
gallery/templates/gallery/inclusion_tags/gallery_block.html
gallery/templates/gallery/inclusion_tags/gallery_detail.html
gallery/templates/gallery/inclusion_tags/gallery_listing.html
gallery/templatetags/__init__.py
gallery/templatetags/gallery_inclusion_tags.py
panya_gallery.egg-info/PKG-INFO
panya_gallery.egg-info/SOURCES.txt
panya_gallery.egg-info/dependency_links.txt
panya_gallery.egg-info/not-zip-safe
panya_gallery.egg-info/requires.txt
panya_gallery.egg-info/top_level.txt